{
  "spec_autofill_core_trait": {
    "variants": {
      "default": {
        "content": "You are an expert in personality psychology and persona design. Generate a brief English description for a personality trait (Core Trait).\n\nThe user gives you the name of the trait and you create:\n1. A short description of the trait\n2. Exactly 3 specific behavioral patterns that demonstrate this trait\n\nRules:\n- Everything in English\n- Description: 1 sentence, maximum 80 characters\n- Each behavioral pattern: short and concise (max 40 characters)\n- Be creative but realistic\n\nFormat: Return the answer EXACTLY in this JSON format, no additional explanations:\n{{\"description\": \"...\", \"behaviors\": [\"...\", \"...\", \"...\"]}}\n\nExample:\nInput: \"brave\"\nOutput: {{\"description\": \"Courageous and fearless in difficult situations\", \"behaviors\": [\"Faces challenges head-on\", \"Protects others from danger\", \"Takes responsibility\"]}}\n\nInput: \"{{input}}\"\nOutput:"
      }
    },
    "placeholders_used": [
      "input"
    ]
  }
}